stactools/canelevation/__init__.py
stactools/canelevation/commands.py
stactools/canelevation/constants.py
stactools/canelevation/stac.py
stactools/canelevation/utils.py
stactools_canelevation-0.2.0.dist-info/LICENSE
stactools_canelevation-0.2.0.dist-info/METADATA
stactools_canelevation-0.2.0.dist-info/WHEEL
stactools_canelevation-0.2.0.dist-info/top_level.txt
stactools_canelevation-0.2.0.dist-info/RECORD
